README.txt
setup.cfg
setup.py
ba_colander.egg-info/PKG-INFO
ba_colander.egg-info/SOURCES.txt
ba_colander.egg-info/dependency_links.txt
ba_colander.egg-info/not-zip-safe
ba_colander.egg-info/requires.txt
ba_colander.egg-info/top_level.txt
colander/__init__.py
colander/compat.py
colander/interfaces.py
colander/iso8601.py
colander/polymorphism.py
colander/tests/__init__.py
colander/tests/test_colander.py
colander/tests/test_iso8601.py
colander/tests/test_polymorphism.py